models.py
operators.py
train.py
utils.py
SharingAttention-0.0.1.dist-info/LICENSE
SharingAttention-0.0.1.dist-info/METADATA
SharingAttention-0.0.1.dist-info/WHEEL
SharingAttention-0.0.1.dist-info/top_level.txt
SharingAttention-0.0.1.dist-info/RECORD
