Metadata-Version: 2.1
Name: SharingAttention
Version: 0.0.1
Summary: Sharing attention in generative adversarial networks
Home-page: https://github.com/shanfenghu/SharingAttention
Author: Shanfeng Hu
Author-email: shanfeng.hu1991@gmail.com
License: UNKNOWN
Platform: UNKNOWN
Classifier: Programming Language :: Python :: 3
Classifier: License :: OSI Approved :: MIT License
Classifier: Operating System :: OS Independent
Requires-Python: >=3.7
